{
  "info": {
    "name": "Notification API - Priority Inbox",
    "description": "Campus Evaluation Notification System API - Stage 6 Implementation",
    "schema": "https://schema.getpostman.com/json/collection/v2.1.0/collection.json"
  },
  "item": [
    {
      "name": "Health Check",
      "request": {
        "method": "GET",
        "header": [],
        "url": {
          "raw": "http://localhost:3000/health",
          "protocol": "http",
          "host": ["localhost"],
          "port": "3000",
          "path": ["health"]
        },
        "description": "Verify the notification API server is running and healthy"
      },
      "response": []
    },
    {
      "name": "Priority Inbox - Top 10",
      "request": {
        "method": "GET",
        "header": [],
        "url": {
          "raw": "http://localhost:3000/api/v1/notifications/priority-inbox?studentId=1042&limit=10",
          "protocol": "http",
          "host": ["localhost"],
          "port": "3000",
          "path": ["api", "v1", "notifications", "priority-inbox"],
          "query": [
            {
              "key": "studentId",
              "value": "1042",
              "disabled": false
            },
            {
              "key": "limit",
              "value": "10",
              "disabled": false
            }
          ]
        },
        "description": "Get top 10 notifications prioritized by type weight and recency\n\nPriority Weights:\n- Placement: 100\n- Result: 50\n- Event: 10\n\nScore = Weight × (1 - Age_Hours/168)"
      },
      "response": []
    },
    {
      "name": "Priority Inbox - Top 5",
      "request": {
        "method": "GET",
        "header": [],
        "url": {
          "raw": "http://localhost:3000/api/v1/notifications/priority-inbox?studentId=1042&limit=5",
          "protocol": "http",
          "host": ["localhost"],
          "port": "3000",
          "path": ["api", "v1", "notifications", "priority-inbox"],
          "query": [
            {
              "key": "studentId",
              "value": "1042",
              "disabled": false
            },
            {
              "key": "limit",
              "value": "5",
              "disabled": false
            }
          ]
        },
        "description": "Get top 5 notifications by priority (useful for mobile display)"
      },
      "response": []
    },
    {
      "name": "All Notifications (Paginated)",
      "request": {
        "method": "GET",
        "header": [],
        "url": {
          "raw": "http://localhost:3000/api/v1/notifications?studentId=1042&limit=20&offset=0",
          "protocol": "http",
          "host": ["localhost"],
          "port": "3000",
          "path": ["api", "v1", "notifications"],
          "query": [
            {
              "key": "studentId",
              "value": "1042",
              "disabled": false
            },
            {
              "key": "limit",
              "value": "20",
              "disabled": false
            },
            {
              "key": "offset",
              "value": "0",
              "disabled": false
            }
          ]
        },
        "description": "Get all notifications with pagination\n\nQuery Parameters:\n- studentId: Student ID\n- limit: Notifications per page (default: 20)\n- offset: Starting position (default: 0)"
      },
      "response": []
    },
    {
      "name": "Page 2 - Notifications",
      "request": {
        "method": "GET",
        "header": [],
        "url": {
          "raw": "http://localhost:3000/api/v1/notifications?studentId=1042&limit=20&offset=20",
          "protocol": "http",
          "host": ["localhost"],
          "port": "3000",
          "path": ["api", "v1", "notifications"],
          "query": [
            {
              "key": "studentId",
              "value": "1042",
              "disabled": false
            },
            {
              "key": "limit",
              "value": "20",
              "disabled": false
            },
            {
              "key": "offset",
              "value": "20",
              "disabled": false
            }
          ]
        },
        "description": "Get second page of notifications (offset=20)"
      },
      "response": []
    },
    {
      "name": "Unread Count",
      "request": {
        "method": "GET",
        "header": [],
        "url": {
          "raw": "http://localhost:3000/api/v1/notifications/count/unread?studentId=1042",
          "protocol": "http",
          "host": ["localhost"],
          "port": "3000",
          "path": ["api", "v1", "notifications", "count", "unread"],
          "query": [
            {
              "key": "studentId",
              "value": "1042",
              "disabled": false
            }
          ]
        },
        "description": "Get count of unread notifications for a student"
      },
      "response": []
    },
    {
      "name": "Different Student - ID 1001",
      "request": {
        "method": "GET",
        "header": [],
        "url": {
          "raw": "http://localhost:3000/api/v1/notifications/priority-inbox?studentId=1001&limit=10",
          "protocol": "http",
          "host": ["localhost"],
          "port": "3000",
          "path": ["api", "v1", "notifications", "priority-inbox"],
          "query": [
            {
              "key": "studentId",
              "value": "1001",
              "disabled": false
            },
            {
              "key": "limit",
              "value": "10",
              "disabled": false
            }
          ]
        },
        "description": "Test with a different student ID"
      },
      "response": []
    },
    {
      "name": "Different Student - ID 2050",
      "request": {
        "method": "GET",
        "header": [],
        "url": {
          "raw": "http://localhost:3000/api/v1/notifications/priority-inbox?studentId=2050&limit=10",
          "protocol": "http",
          "host": ["localhost"],
          "port": "3000",
          "path": ["api", "v1", "notifications", "priority-inbox"],
          "query": [
            {
              "key": "studentId",
              "value": "2050",
              "disabled": false
            },
            {
              "key": "limit",
              "value": "10",
              "disabled": false
            }
          ]
        },
        "description": "Test with another different student ID"
      },
      "response": []
    }
  ],
  "variable": [
    {
      "key": "base_url",
      "value": "http://localhost:3000",
      "type": "string"
    },
    {
      "key": "studentId",
      "value": "1042",
      "type": "string"
    }
  ]
}
